pyemailnator/__init__.py
pyemailnator/create_client.py
pyemailnator/validate_proxy.py
pyemailnator-0.0.1.dist-info/METADATA
pyemailnator-0.0.1.dist-info/WHEEL
pyemailnator-0.0.1.dist-info/top_level.txt
pyemailnator-0.0.1.dist-info/RECORD
