Metadata-Version: 2.1
Name: pyemailnator
Version: 0.0.1
Summary: EmailNator Lib
Home-page: https://github.com/nazavod777/pyemailnator
Author: nazavod
Author-email: n4z4v0d@gmail.com
License: UNKNOWN
Project-URL: GitHub, https://github.com/nazavod777/pyemailnator
Keywords: emailnator smartnator email temp_mail free_mail
Platform: UNKNOWN
Classifier: Programming Language :: Python :: 3.11
Classifier: License :: OSI Approved :: MIT License
Classifier: Operating System :: OS Independent
Requires-Python: >=3.11
Requires-Dist: better-proxy (>=0.2.2)
Requires-Dist: httpx (>=0.24.1)
Requires-Dist: requests (>=2.31.0)
